postcrawl/__init__.py
postcrawl/client.py
postcrawl/constants.py
postcrawl/exceptions.py
postcrawl/generated_types.py
postcrawl/py.typed
postcrawl/types.py
postcrawl-1.1.0.dist-info/METADATA
postcrawl-1.1.0.dist-info/WHEEL
postcrawl-1.1.0.dist-info/licenses/LICENSE
postcrawl-1.1.0.dist-info/RECORD
