Metadata-Version: 2.4
Name: postcrawl
Version: 1.1.0
Summary: Python SDK for PostCrawl - The Fastest LLM Ready Social Media Crawler
Project-URL: Homepage, https://postcrawl.com/
Project-URL: Documentation, https://github.com/post-crawl/python-sdk
Project-URL: Repository, https://github.com/post-crawl/python-sdk
Project-URL: Issues, https://github.com/post-crawl/python-sdk/issues
Project-URL: Changelog, https://github.com/post-crawl/python-sdk/releases
Author-email: PostCrawl Team <support@postcrawl.com>
License: MIT
License-File: LICENSE
Keywords: api,postcrawl,reddit,scraping,sdk,social-media,tiktok
Classifier: Development Status :: 5 - Production/Stable
Classifier: Intended Audience :: Developers
Classifier: License :: OSI Approved :: MIT License
Classifier: Programming Language :: Python :: 3
Classifier: Programming Language :: Python :: 3.10
Classifier: Programming Language :: Python :: 3.11
Classifier: Programming Language :: Python :: 3.12
Classifier: Programming Language :: Python :: 3.13
Classifier: Topic :: Internet :: WWW/HTTP
Classifier: Topic :: Software Development :: Libraries :: Python Modules
Classifier: Typing :: Typed
Requires-Python: >=3.10
Requires-Dist: httpx<1.0,>=0.25
Requires-Dist: pydantic<3.0,>=2.0
Requires-Dist: python-dotenv>=1.1.1
Requires-Dist: typing-extensions<5.0,>=4.8
Provides-Extra: dev
Requires-Dist: black>=23.0; extra == 'dev'
Requires-Dist: mypy>=1.5; extra == 'dev'
Requires-Dist: pytest-asyncio>=0.21; extra == 'dev'
Requires-Dist: pytest-httpx>=0.22; extra == 'dev'
Requires-Dist: pytest>=7.4; extra == 'dev'
Requires-Dist: ruff>=0.1.0; extra == 'dev'
